tf_fast_api/__init__.py
tf_fast_api-0.0.1.dist-info/METADATA
tf_fast_api-0.0.1.dist-info/WHEEL
tf_fast_api-0.0.1.dist-info/top_level.txt
tf_fast_api-0.0.1.dist-info/RECORD
